{
  "arquivo": "Relatório Financeiro Técnico (24).xlsx",
  "dataDetecao": "2025-10-31T19:47:33.427Z",
  "totalPlanilhas": 1,
  "planilhas": [
    {
      "nome": "Sheet1",
      "totalLinhas": 221,
      "totalColunas": 13,
      "colunas": [
        {
          "nome": "Relatório Financeiro: Técnico",
          "tipo": "texto",
          "formato": null,
          "totalValores": 221,
          "valoresUnicos": 174,
          "exemplos": [
            "Nome tecnico",
            "4135 Sérgio Fajardo - LINHA BRANCA (GERAL)",
            "28435 Flávio Troitinho Alves  - Linha Branca",
            "39864 Antonio Eberson da Rosa Pivoto   Pivoto -  L",
            "41723 jarbas - Refrigeração"
          ],
          "distribuicaoTipos": {
            "texto": 221
          }
        },
        {
          "nome": "__EMPTY",
          "tipo": "cpf",
          "formato": "cpf",
          "totalValores": 221,
          "valoresUnicos": 174,
          "exemplos": [
            "CPF/CNPJ",
            "975.205.787-04",
            "960.637.697-49",
            "951.787.590-87",
            "94.311.315/104 -"
          ],
          "distribuicaoTipos": {
            "texto": 4,
            "cpf": 100,
            "cnpj": 93,
            "telefone": 4,
            "numero_texto": 20
          }
        },
        {
          "nome": "__EMPTY_1",
          "tipo": "texto",
          "formato": null,
          "totalValores": 220,
          "valoresUnicos": 173,
          "exemplos": [
            "Favorecido",
            "Sérgio Murilo da Silva fajardo",
            "Flávio Troitinho alves",
            "Antonio Eberson da Rosa Pivoto",
            "Jarbas Augusto Rodrigues"
          ],
          "distribuicaoTipos": {
            "codigo": 4,
            "texto": 216
          }
        },
        {
          "nome": "__EMPTY_2",
          "tipo": "codigo",
          "formato": null,
          "totalValores": 221,
          "valoresUnicos": 221,
          "exemplos": [
            "Identificador",
            "25319034769011f39cc095",
            "206501061268fa1026a282a",
            "127729943568f9453f25ec4",
            "188102076469023900b3abc"
          ],
          "distribuicaoTipos": {
            "codigo": 221
          }
        },
        {
          "nome": "__EMPTY_3",
          "tipo": "numero_texto",
          "formato": "numero: 4103483 a 70426317",
          "totalValores": 221,
          "valoresUnicos": 220,
          "exemplos": [
            "Sinistros",
            "45257325",
            "SVO-19395222",
            "SVO-19425071",
            "00811789/01"
          ],
          "distribuicaoTipos": {
            "codigo": 40,
            "numero_texto": 145,
            "texto": 36
          }
        },
        {
          "nome": "__EMPTY_4",
          "tipo": "texto",
          "formato": null,
          "totalValores": 83,
          "valoresUnicos": 25,
          "exemplos": [
            "Nº NF",
            "A GERAR",
            "11728 E 20253534",
            "378743",
            "377766/377553"
          ],
          "distribuicaoTipos": {
            "texto": 48,
            "numero_texto": 33,
            "codigo": 2
          }
        },
        {
          "nome": "__EMPTY_5",
          "tipo": "texto",
          "formato": null,
          "totalValores": 221,
          "valoresUnicos": 2,
          "exemplos": [
            "Descrição",
            "Pagamento ao técnico"
          ],
          "distribuicaoTipos": {
            "texto": 221
          }
        },
        {
          "nome": "__EMPTY_6",
          "tipo": "numero_texto",
          "formato": "numero: 0 a 0",
          "totalValores": 221,
          "valoresUnicos": 2,
          "exemplos": [
            "Mensalidade",
            "0.00"
          ],
          "distribuicaoTipos": {
            "codigo": 1,
            "numero_texto": 220
          }
        },
        {
          "nome": "__EMPTY_7",
          "tipo": "numero_texto",
          "formato": "numero: 20 a 1549.99",
          "totalValores": 221,
          "valoresUnicos": 72,
          "exemplos": [
            "Valor pago",
            "380.00",
            "534.44",
            "150.00",
            "450.00"
          ],
          "distribuicaoTipos": {
            "texto": 1,
            "numero_texto": 220
          }
        },
        {
          "nome": "__EMPTY_8",
          "tipo": "data_texto",
          "formato": "data",
          "totalValores": 221,
          "valoresUnicos": 2,
          "exemplos": [
            "Data Pagamento",
            "29/10/2025"
          ],
          "distribuicaoTipos": {
            "texto": 1,
            "data_texto": 220
          }
        },
        {
          "nome": "__EMPTY_9",
          "tipo": "texto",
          "formato": null,
          "totalValores": 221,
          "valoresUnicos": 20,
          "exemplos": [
            "Seguradora",
            "MERCADO LIVRE - ASSURANT BRANCA",
            "ELECTROLUX",
            "EUROP ASSISTANCE",
            "EOS Frigelar"
          ],
          "distribuicaoTipos": {
            "codigo": 37,
            "texto": 184
          }
        },
        {
          "nome": "__EMPTY_10",
          "tipo": "texto",
          "formato": null,
          "totalValores": 221,
          "valoresUnicos": 44,
          "exemplos": [
            "Usuário",
            "fabio.pereira",
            "samara.rodrigues",
            "pedro.cruz",
            "marcos.vinicius"
          ],
          "distribuicaoTipos": {
            "texto": 221
          }
        },
        {
          "nome": "__EMPTY_11",
          "tipo": "texto",
          "formato": null,
          "totalValores": 221,
          "valoresUnicos": 2,
          "exemplos": [
            "AÇÃO",
            " "
          ],
          "distribuicaoTipos": {
            "texto": 221
          }
        }
      ]
    }
  ]
}